registry/__init__.py
registry/admin.py
registry/apps.py
registry/helper.py
registry/migrations/0001_initial.py
registry/migrations/0002_auto_20200404_0726.py
registry/migrations/__init__.py
registry/models.py
registry/tests.py
registry/views.py
dj_registry-0.2.3.dist-info/LICENSE
dj_registry-0.2.3.dist-info/METADATA
dj_registry-0.2.3.dist-info/WHEEL
dj_registry-0.2.3.dist-info/RECORD
